ssnapshot/__init__.py
ssnapshot/command_line.py
ssnapshot/ssnapshot.py
ssnapshot-0.0.1.dist-info/LICENSE
ssnapshot-0.0.1.dist-info/METADATA
ssnapshot-0.0.1.dist-info/WHEEL
ssnapshot-0.0.1.dist-info/entry_points.txt
ssnapshot-0.0.1.dist-info/top_level.txt
ssnapshot-0.0.1.dist-info/RECORD
