Metadata-Version: 2.1
Name: ssnapshot
Version: 0.0.1
Summary: A utility to generate a snapshot of slurm's state
Home-page: https://github.com/ilifu/ssnapshot
Author: Dane Kennedy
Author-email: dane@idia.ac.za
License: UNKNOWN
Platform: UNKNOWN
Classifier: Programming Language :: Python :: 3.8
Classifier: License :: OSI Approved :: MIT License
Classifier: Operating System :: OS Independent
Classifier: Development Status :: 2 - Pre-Alpha
Classifier: Environment :: Console
Classifier: Intended Audience :: System Administrators
Classifier: Topic :: Scientific/Engineering
Classifier: Topic :: System :: Clustering
Classifier: Topic :: System :: Logging
Classifier: Topic :: System :: Systems Administration
Requires-Python: >=3.6
Requires-Dist: coloredlogs
Requires-Dist: humanize
Requires-Dist: pandas
Requires-Dist: jinja2
Requires-Dist: tabulate
